qqwry/__init__.py
qqwry/shell/__init__.py
qqwry/shell/usage.py
qqwry/src/__init__.py
qqwry/src/qqwry.py
qqwry/src/update_qqwry.py
qqwry_linux_python3-0.0.7.dist-info/LICENSE
qqwry_linux_python3-0.0.7.dist-info/METADATA
qqwry_linux_python3-0.0.7.dist-info/WHEEL
qqwry_linux_python3-0.0.7.dist-info/entry_points.txt
qqwry_linux_python3-0.0.7.dist-info/top_level.txt
qqwry_linux_python3-0.0.7.dist-info/zip-safe
qqwry_linux_python3-0.0.7.dist-info/RECORD
