Metadata-Version: 2.1
Name: qqwry-linux-python3
Version: 0.0.7
Summary: Using and downloading qqwry.dat, for Python 3.6+
Home-page: https://github.com/lqshome/qqwry-linux-python3
Author: unclear
Author-email: qsykgg@gmail.com
License: MIT License
Platform: UNKNOWN
Classifier: Programming Language :: Python :: 3
Classifier: License :: OSI Approved :: MIT License
Classifier: Operating System :: OS Independent
Requires-Python: >=3.6
